cs/iso14496.py
cs_iso14496-20241122.dist-info/METADATA
cs_iso14496-20241122.dist-info/WHEEL
cs_iso14496-20241122.dist-info/top_level.txt
cs_iso14496-20241122.dist-info/RECORD
