Metadata-Version: 2.1
Name: cs-iso14496
Version: 20241122
Summary: Facilities for ISO14496 files - the ISO Base Media File Format, the basis for several things including MP4 and MOV.
Author-email: Cameron Simpson <cs@cskk.id.au>
License: GNU General Public License v3 or later (GPLv3+)
Project-URL: Monorepo Hg/Mercurial Mirror, https://hg.sr.ht/~cameron-simpson/css
Project-URL: Monorepo Git Mirror, https://github.com/cameron-simpson/css
Project-URL: MonoRepo Commits, https://bitbucket.org/cameron_simpson/css/commits/branch/main
Project-URL: Source, https://github.com/cameron-simpson/css/blob/main/lib/python/cs/iso14496.py
Keywords: python3
Classifier: Development Status :: 4 - Beta
Classifier: Environment :: Console
Classifier: Intended Audience :: Developers
Classifier: Programming Language :: Python :: 3
Classifier: Topic :: Multimedia :: Video
Classifier: Operating System :: OS Independent
Classifier: License :: OSI Approved :: GNU General Public License v3 or later (GPLv3+)
Requires-Dist: cs.binary>=20240630
Requires-Dist: cs.buffer>=20240630
Requires-Dist: cs.cmdutils>=20241122.2
Requires-Dist: cs.fs>=20241122
Requires-Dist: cs.fstags>=20241122
Requires-Dist: cs.imageutils>=20240422.1
Requires-Dist: cs.lex>=20241122
Requires-Dist: cs.logutils>=20241109
Requires-Dist: cs.pfx>=20240630
Requires-Dist: cs.py.func>=20240630
Requires-Dist: cs.tagset>=20241007
Requires-Dist: cs.threads>=20241005
Requires-Dist: cs.units
Requires-Dist: cs.upd>=20240630
Requires-Dist: icontract
Requires-Dist: typeguard
